[
    {
        "title": "Backpack Smiley",
        "price": 291.99,
        "quantity": 0,
        "image": "assets/images/bag.png"
    },
    {
        "title": "Backpack Smiley",
        "price": 232.99,
        "quantity": 0,
        "image": "assets/images/bag.png"
    },
    {
        "title": "Backpack Smiley",
        "price": 293.99,
        "quantity": 0,
        "image": "assets/images/bag.png"
    },
    {
        "title": "Backpack Smiley",
        "price": 234.99,
        "quantity": 0,
        "image": "assets/images/bag.png"
    },
    {
        "title": "Backpack Smiley",
        "price": 295.99,
        "quantity": 0,
        "image": "assets/images/bag.png"
    },
    {
        "title": "Backpack Smiley",
        "price": 236.99,
        "quantity": 0,
        "image": "assets/images/bag.png"
    },
    {
        "title": "Backpack Smiley",
        "price": 297.99,
        "quantity": 0,
        "image": "assets/images/bag.png"
    },
    {
        "title": "Backpack Smiley",
        "price": 238.99,
        "quantity": 0,
        "image": "assets/images/bag.png"
    },
    {
        "title": "Backpack Smiley",
        "price": 219.99,
        "quantity": 0,
        "image": "assets/images/bag.png"
    },
    {
        "title": "Backpack Smiley",
        "price": 210.99,
        "quantity": 0,
        "image": "assets/images/bag.png"
    }
]